monitor/__init__.py
monitor/performance.py
monitor/security.py
monitor/seo.py
monitor/ui.py
report/__init__.py
report/pdf_report.py
report/xlsx_report.py
package_server_report_website_side-2.0.0.dist-info/METADATA
package_server_report_website_side-2.0.0.dist-info/WHEEL
package_server_report_website_side-2.0.0.dist-info/top_level.txt
package_server_report_website_side-2.0.0.dist-info/RECORD
