Metadata-Version: 2.1
Name: package_server_report_website_side
Version: 2.0.0
Summary: A web application for monitoring and reporting
Author: Nishal
Author-email: your.email@example.com
Classifier: Programming Language :: Python :: 3
Classifier: Programming Language :: Python :: 3.8
Classifier: License :: OSI Approved :: MIT License
Classifier: Operating System :: OS Independent
Requires-Python: >=3.6
Requires-Dist: flask
